[
    {
        "Model Rank": 1,
        "Trial ID": "0073",
        "train_loss": 4.160110585378321,
        "train_mse": 4.160110585378321,
        "train_rmse": 2.0396349147282025,
        "train_mape": 51.444863426766275,
        "train_r2": 0.3858624730545923,
        "val_loss": 1.3261684951345147,
        "val_mse": 1.3261684951345147,
        "val_rmse": 1.1515938933211285,
        "val_mape": 41.295819709636696,
        "val_r2": 0.309376229198689,
        "test_loss": 1.284006707057279,
        "test_mse": 1.284006707057279,
        "test_rmse": 1.133140197441287,
        "test_mape": 43.33514562595597,
        "test_r2": 0.5093172314434681,
        "num_lstm_layers": 2,
        "units_lstm_0": 96,
        "dropout": 0.35000000000000003,
        "num_lstm_layers_after": 1,
        "units_lstm_after_0": 64,
        "dense_units": 12,
        "dense_activation": "elu",
        "dropout_2": 0.05,
        "optimizer": "rmsprop",
        "learning_rate": 0.00024026393786951466,
        "batch_size": 32,
        "units_lstm_1": 96,
        "units_lstm_after_1": 64,
        "units_lstm_after_2": 64,
        "units_lstm_2": 128,
        "tuner/epochs": 50,
        "tuner/initial_epoch": 17,
        "tuner/bracket": 2,
        "tuner/round": 2,
        "tuner/trial_id": "0069"
    },
    {
        "Model Rank": 9,
        "Trial ID": "0068",
        "train_loss": 4.8621768434091726,
        "train_mse": 4.8621768434091726,
        "train_rmse": 2.2050344313432326,
        "train_mape": 54.907043099747554,
        "train_r2": 0.282219738898843,
        "val_loss": 1.3742381135365207,
        "val_mse": 1.3742381135365207,
        "val_rmse": 1.172279025461311,
        "val_mape": 42.45660053661406,
        "val_r2": 0.28434319512830397,
        "test_loss": 1.2653658510757138,
        "test_mse": 1.2653658510757138,
        "test_rmse": 1.1248848168037977,
        "test_mape": 43.68210297416131,
        "test_r2": 0.5164408288289216,
        "num_lstm_layers": 2,
        "units_lstm_0": 96,
        "dropout": 0.0,
        "num_lstm_layers_after": 2,
        "units_lstm_after_0": 64,
        "dense_units": 20,
        "dense_activation": "elu",
        "dropout_2": 0.0,
        "optimizer": "adam",
        "learning_rate": 0.0002452567376517019,
        "batch_size": 16,
        "units_lstm_1": 128,
        "units_lstm_after_1": 64,
        "units_lstm_after_2": 64,
        "units_lstm_2": 96,
        "tuner/epochs": 17,
        "tuner/initial_epoch": 6,
        "tuner/bracket": 2,
        "tuner/round": 1,
        "tuner/trial_id": "0053"
    },
    {
        "Model Rank": 7,
        "Trial ID": "0083",
        "train_loss": 5.050209385090692,
        "train_mse": 5.050209385090692,
        "train_rmse": 2.2472670925127463,
        "train_mape": 55.67111847814669,
        "train_r2": 0.2544613806139884,
        "val_loss": 1.3981785798930504,
        "val_mse": 1.3981785798930504,
        "val_rmse": 1.1824460156358303,
        "val_mape": 43.21084843699198,
        "val_r2": 0.2718758086607862,
        "test_loss": 1.3285411609232447,
        "test_mse": 1.3285411609232447,
        "test_rmse": 1.1526235989789748,
        "test_mape": 43.22489392056519,
        "test_r2": 0.4922984035829916,
        "num_lstm_layers": 2,
        "units_lstm_0": 128,
        "dropout": 0.1,
        "num_lstm_layers_after": 1,
        "units_lstm_after_0": 64,
        "dense_units": 16,
        "dense_activation": "elu",
        "dropout_2": 0.4,
        "optimizer": "rmsprop",
        "learning_rate": 0.000622976896229868,
        "batch_size": 32,
        "units_lstm_1": 128,
        "units_lstm_after_1": 64,
        "units_lstm_after_2": 64,
        "units_lstm_2": 128,
        "tuner/epochs": 50,
        "tuner/initial_epoch": 17,
        "tuner/bracket": 1,
        "tuner/round": 1,
        "tuner/trial_id": "0081"
    },
    {
        "Model Rank": 4,
        "Trial ID": "0072",
        "train_loss": 4.652360453935186,
        "train_mse": 4.652360453935186,
        "train_rmse": 2.156933112995205,
        "train_mape": 54.43125231045794,
        "train_r2": 0.31319394400701095,
        "val_loss": 1.4265340692684645,
        "val_mse": 1.4265340692684645,
        "val_rmse": 1.194376016700128,
        "val_mape": 43.0781135944699,
        "val_r2": 0.25710922728955665,
        "test_loss": 1.302940639607337,
        "test_mse": 1.302940639607337,
        "test_rmse": 1.1414642524439111,
        "test_mape": 43.843860408242364,
        "test_r2": 0.5020816349374206,
        "num_lstm_layers": 2,
        "units_lstm_0": 96,
        "dropout": 0.0,
        "num_lstm_layers_after": 2,
        "units_lstm_after_0": 64,
        "dense_units": 20,
        "dense_activation": "elu",
        "dropout_2": 0.0,
        "optimizer": "adam",
        "learning_rate": 0.0002452567376517019,
        "batch_size": 16,
        "units_lstm_1": 128,
        "units_lstm_after_1": 64,
        "units_lstm_after_2": 64,
        "units_lstm_2": 96,
        "tuner/epochs": 50,
        "tuner/initial_epoch": 17,
        "tuner/bracket": 2,
        "tuner/round": 2,
        "tuner/trial_id": "0068"
    },
    {
        "Model Rank": 2,
        "Trial ID": "0051",
        "train_loss": 4.248435070750842,
        "train_mse": 4.248435070750842,
        "train_rmse": 2.0611732267693665,
        "train_mape": 50.860327941235425,
        "train_r2": 0.37282354538616524,
        "val_loss": 1.491738841092306,
        "val_mse": 1.491738841092306,
        "val_rmse": 1.221367610955975,
        "val_mape": 44.47510709762934,
        "val_r2": 0.2231527839292784,
        "test_loss": 1.345956853713818,
        "test_mse": 1.345956853713818,
        "test_rmse": 1.1601538060592733,
        "test_mape": 43.7984323665406,
        "test_r2": 0.4856430019345114,
        "num_lstm_layers": 2,
        "units_lstm_0": 128,
        "dropout": 0.35000000000000003,
        "num_lstm_layers_after": 1,
        "units_lstm_after_0": 64,
        "dense_units": 12,
        "dense_activation": "elu",
        "dropout_2": 0.4,
        "optimizer": "rmsprop",
        "learning_rate": 0.00010277817095870274,
        "batch_size": 16,
        "units_lstm_1": 96,
        "units_lstm_after_1": 64,
        "units_lstm_after_2": 64,
        "units_lstm_2": 96,
        "tuner/epochs": 50,
        "tuner/initial_epoch": 17,
        "tuner/bracket": 3,
        "tuner/round": 3,
        "tuner/trial_id": "0047"
    },
    {
        "Model Rank": 3,
        "Trial ID": "0084",
        "train_loss": 4.413049855848048,
        "train_mse": 4.413049855848048,
        "train_rmse": 2.1007260306494153,
        "train_mape": 53.410275632443,
        "train_r2": 0.34852224018202616,
        "val_loss": 1.5059556111623458,
        "val_mse": 1.5059556111623458,
        "val_rmse": 1.2271738308660047,
        "val_mape": 45.233106433392685,
        "val_r2": 0.2157491701423363,
        "test_loss": 1.4684629547955683,
        "test_mse": 1.4684629547955683,
        "test_rmse": 1.2118015327583838,
        "test_mape": 45.71536331663973,
        "test_r2": 0.43882733304939703,
        "num_lstm_layers": 2,
        "units_lstm_0": 96,
        "dropout": 0.1,
        "num_lstm_layers_after": 3,
        "units_lstm_after_0": 64,
        "dense_units": 16,
        "dense_activation": "elu",
        "dropout_2": 0.05,
        "optimizer": "adam",
        "learning_rate": 0.00028950106746006277,
        "batch_size": 32,
        "units_lstm_1": 128,
        "units_lstm_after_1": 64,
        "units_lstm_after_2": 64,
        "units_lstm_2": 64,
        "tuner/epochs": 50,
        "tuner/initial_epoch": 17,
        "tuner/bracket": 1,
        "tuner/round": 1,
        "tuner/trial_id": "0078"
    },
    {
        "Model Rank": 6,
        "Trial ID": "0082",
        "train_loss": 5.324159918043262,
        "train_mse": 5.324159918043262,
        "train_rmse": 2.307414119321294,
        "train_mape": 57.64302618597984,
        "train_r2": 0.21401935404762795,
        "val_loss": 1.5075997814345783,
        "val_mse": 1.5075997814345783,
        "val_rmse": 1.2278435492498945,
        "val_mape": 45.70869532594889,
        "val_r2": 0.21489294178416418,
        "test_loss": 1.4159233616119016,
        "test_mse": 1.4159233616119016,
        "test_rmse": 1.1899257798753256,
        "test_mape": 45.205970016002134,
        "test_r2": 0.4589053224403399,
        "num_lstm_layers": 1,
        "units_lstm_0": 128,
        "dropout": 0.1,
        "num_lstm_layers_after": 3,
        "units_lstm_after_0": 64,
        "dense_units": 48,
        "dense_activation": "relu",
        "dropout_2": 0.25,
        "optimizer": "rmsprop",
        "learning_rate": 0.000622976896229868,
        "batch_size": 32,
        "units_lstm_1": 128,
        "units_lstm_after_1": 64,
        "units_lstm_after_2": 64,
        "units_lstm_2": 32,
        "tuner/epochs": 50,
        "tuner/initial_epoch": 17,
        "tuner/bracket": 1,
        "tuner/round": 1,
        "tuner/trial_id": "0076"
    },
    {
        "Model Rank": 10,
        "Trial ID": "0076",
        "train_loss": 4.443252766374335,
        "train_mse": 4.443252766374335,
        "train_rmse": 2.107902456560629,
        "train_mape": 53.49937665701378,
        "train_r2": 0.3440635267905213,
        "val_loss": 1.5912086701434784,
        "val_mse": 1.5912086701434784,
        "val_rmse": 1.2614311991319536,
        "val_mape": 46.058310192810005,
        "val_r2": 0.17135225581213698,
        "test_loss": 1.4901066616467045,
        "test_mse": 1.4901066616467045,
        "test_rmse": 1.2206992511043433,
        "test_mape": 45.82518316054143,
        "test_r2": 0.43055619712684323,
        "num_lstm_layers": 1,
        "units_lstm_0": 128,
        "dropout": 0.1,
        "num_lstm_layers_after": 3,
        "units_lstm_after_0": 64,
        "dense_units": 48,
        "dense_activation": "relu",
        "dropout_2": 0.25,
        "optimizer": "rmsprop",
        "learning_rate": 0.000622976896229868,
        "batch_size": 32,
        "units_lstm_1": 128,
        "units_lstm_after_1": 64,
        "units_lstm_after_2": 64,
        "units_lstm_2": 32,
        "tuner/epochs": 17,
        "tuner/initial_epoch": 0,
        "tuner/bracket": 1,
        "tuner/round": 0
    },
    {
        "Model Rank": 5,
        "Trial ID": "0050",
        "train_loss": 4.300892010726432,
        "train_mse": 4.300892010726432,
        "train_rmse": 2.0738592070645567,
        "train_mape": 51.9068565839921,
        "train_r2": 0.36507957446842987,
        "val_loss": 1.625348088119232,
        "val_mse": 1.625348088119232,
        "val_rmse": 1.27489140248071,
        "val_mape": 46.00380206790017,
        "val_r2": 0.15357359973496532,
        "test_loss": 1.5614729888032084,
        "test_mse": 1.5614729888032084,
        "test_rmse": 1.2495891279949616,
        "test_mape": 46.41695436803956,
        "test_r2": 0.4032835771331983,
        "num_lstm_layers": 1,
        "units_lstm_0": 128,
        "dropout": 0.0,
        "num_lstm_layers_after": 3,
        "units_lstm_after_0": 64,
        "dense_units": 8,
        "dense_activation": "elu",
        "dropout_2": 0.25,
        "optimizer": "rmsprop",
        "learning_rate": 0.00024026393786951466,
        "batch_size": 24,
        "units_lstm_1": 64,
        "units_lstm_after_1": 64,
        "units_lstm_after_2": 64,
        "units_lstm_2": 64,
        "tuner/epochs": 50,
        "tuner/initial_epoch": 17,
        "tuner/bracket": 3,
        "tuner/round": 3,
        "tuner/trial_id": "0046"
    },
    {
        "Model Rank": 8,
        "Trial ID": "0046",
        "train_loss": 3.859409727166018,
        "train_mse": 3.859409727166018,
        "train_rmse": 1.9645380442144709,
        "train_mape": 48.25173181232371,
        "train_r2": 0.43025352411509465,
        "val_loss": 1.6325380741866142,
        "val_mse": 1.6325380741866142,
        "val_rmse": 1.2777081334117797,
        "val_mape": 44.979040502985484,
        "val_r2": 0.1498292977793071,
        "test_loss": 1.524399892977101,
        "test_mse": 1.524399892977101,
        "test_rmse": 1.2346659033832192,
        "test_mape": 45.3337619650436,
        "test_r2": 0.41745104931144483,
        "num_lstm_layers": 1,
        "units_lstm_0": 128,
        "dropout": 0.0,
        "num_lstm_layers_after": 3,
        "units_lstm_after_0": 64,
        "dense_units": 8,
        "dense_activation": "elu",
        "dropout_2": 0.25,
        "optimizer": "rmsprop",
        "learning_rate": 0.00024026393786951466,
        "batch_size": 24,
        "units_lstm_1": 64,
        "units_lstm_after_1": 64,
        "units_lstm_after_2": 64,
        "units_lstm_2": 64,
        "tuner/epochs": 17,
        "tuner/initial_epoch": 6,
        "tuner/bracket": 3,
        "tuner/round": 2,
        "tuner/trial_id": "0034"
    }
]