[
    {
        "Model Rank": 6,
        "Trial ID": "0088",
        "train_loss": 8.850330634067554,
        "train_mse": 8.850330634067554,
        "train_rmse": 2.9749505263226736,
        "train_mape": 34.04212180843657,
        "train_r2": 0.648320585800527,
        "val_loss": 7.75097995019781,
        "val_mse": 7.75097995019781,
        "val_rmse": 2.784058180102889,
        "val_mape": 29.846964820982503,
        "val_r2": 0.7185509390976264,
        "test_loss": 3.2463188036361434,
        "test_mse": 3.2463188036361434,
        "test_rmse": 1.8017543682855728,
        "test_mape": 27.940200146128475,
        "test_r2": 0.6548765469142481,
        "num_tcnn_layers_input": 2,
        "units_lstm_0": 64,
        "dropout": 0.30000000000000004,
        "num_tcnn_layers_after_input": 1,
        "units_lstm_1": 64,
        "units_lstm_2": 128,
        "dense_units": 16,
        "dense_activation": "sigmoid",
        "output_activation": "elu",
        "optimizer": "adam",
        "learning_rate": 0.00100156290693203,
        "units_lstm_3": 64,
        "units_lstm_4": 64,
        "units_lstm_5": 64,
        "units_lstm_6": 64,
        "batch_size": 24,
        "tuner/epochs": 50,
        "tuner/initial_epoch": 0,
        "tuner/bracket": 0,
        "tuner/round": 0
    },
    {
        "Model Rank": 2,
        "Trial ID": "0084",
        "train_loss": 8.65437780001528,
        "train_mse": 8.65437780001528,
        "train_rmse": 2.9418323881579793,
        "train_mape": 34.03165377736454,
        "train_r2": 0.6561070268657868,
        "val_loss": 7.863147486412997,
        "val_mse": 7.863147486412997,
        "val_rmse": 2.8041304332025994,
        "val_mape": 29.813364238313078,
        "val_r2": 0.7144779769774376,
        "test_loss": 2.768969436265814,
        "test_mse": 2.768969436265814,
        "test_rmse": 1.6640220660393341,
        "test_mape": 26.32342134598543,
        "test_r2": 0.7056246317328494,
        "num_tcnn_layers_input": 3,
        "units_lstm_0": 96,
        "dropout": 0.30000000000000004,
        "num_tcnn_layers_after_input": 1,
        "units_lstm_1": 32,
        "units_lstm_2": 128,
        "dense_units": 12,
        "dense_activation": "sigmoid",
        "output_activation": "tanh",
        "optimizer": "adam",
        "learning_rate": 0.0008788815784436897,
        "units_lstm_3": 64,
        "units_lstm_4": 64,
        "units_lstm_5": 64,
        "units_lstm_6": 64,
        "batch_size": 24,
        "tuner/epochs": 50,
        "tuner/initial_epoch": 17,
        "tuner/bracket": 1,
        "tuner/round": 1,
        "tuner/trial_id": "0077"
    },
    {
        "Model Rank": 10,
        "Trial ID": "0081",
        "train_loss": 13.892858053561204,
        "train_mse": 13.892858053561204,
        "train_rmse": 3.7273124437805323,
        "train_mape": 42.538846740521066,
        "train_r2": 0.4479491915221998,
        "val_loss": 9.305719272039637,
        "val_mse": 9.305719272039637,
        "val_rmse": 3.0505277038636507,
        "val_mape": 32.97143057059801,
        "val_r2": 0.6620961521039883,
        "test_loss": 2.233092561928819,
        "test_mse": 2.233092561928819,
        "test_rmse": 1.4943535598809337,
        "test_mape": 24.14504265393766,
        "test_r2": 0.7625949074472466,
        "num_tcnn_layers_input": 1,
        "units_lstm_0": 32,
        "dropout": 0.15000000000000002,
        "num_tcnn_layers_after_input": 3,
        "units_lstm_1": 128,
        "units_lstm_2": 96,
        "dense_units": 32,
        "dense_activation": "relu",
        "output_activation": "elu",
        "optimizer": "adam",
        "learning_rate": 0.0026852909715998317,
        "units_lstm_3": 64,
        "units_lstm_4": 64,
        "units_lstm_5": 64,
        "units_lstm_6": 64,
        "batch_size": 32,
        "tuner/epochs": 17,
        "tuner/initial_epoch": 0,
        "tuner/bracket": 1,
        "tuner/round": 0
    },
    {
        "Model Rank": 4,
        "Trial ID": "0089",
        "train_loss": 9.1098135653099,
        "train_mse": 9.1098135653099,
        "train_rmse": 3.0182467701150446,
        "train_mape": 33.712263613705076,
        "train_r2": 0.6380096935833703,
        "val_loss": 9.83322708572106,
        "val_mse": 9.83322708572106,
        "val_rmse": 3.135797679334727,
        "val_mape": 34.52941397608789,
        "val_r2": 0.6429415961983816,
        "test_loss": 4.720270211554887,
        "test_mse": 4.720270211554887,
        "test_rmse": 2.172618284824761,
        "test_mape": 34.444944049762384,
        "test_r2": 0.4981774577761936,
        "num_tcnn_layers_input": 2,
        "units_lstm_0": 128,
        "dropout": 0.15000000000000002,
        "num_tcnn_layers_after_input": 3,
        "units_lstm_1": 64,
        "units_lstm_2": 128,
        "dense_units": 12,
        "dense_activation": "relu",
        "output_activation": "elu",
        "optimizer": "rmsprop",
        "learning_rate": 0.0008788815784436897,
        "units_lstm_3": 64,
        "units_lstm_4": 64,
        "units_lstm_5": 64,
        "units_lstm_6": 64,
        "batch_size": 32,
        "tuner/epochs": 50,
        "tuner/initial_epoch": 0,
        "tuner/bracket": 0,
        "tuner/round": 0
    },
    {
        "Model Rank": 8,
        "Trial ID": "0086",
        "train_loss": 10.688375860044733,
        "train_mse": 10.688375860044733,
        "train_rmse": 3.269308162294392,
        "train_mape": 35.941272737769616,
        "train_r2": 0.575283464921043,
        "val_loss": 10.976465557019504,
        "val_mse": 10.976465557019504,
        "val_rmse": 3.3130749398435744,
        "val_mape": 36.400698533951555,
        "val_r2": 0.6014289879602193,
        "test_loss": 5.365922295162611,
        "test_mse": 5.365922295162611,
        "test_rmse": 2.3164460484031593,
        "test_mape": 36.756529000109325,
        "test_r2": 0.4295367326763909,
        "num_tcnn_layers_input": 1,
        "units_lstm_0": 64,
        "dropout": 0.25,
        "num_tcnn_layers_after_input": 1,
        "units_lstm_1": 128,
        "units_lstm_2": 96,
        "dense_units": 40,
        "dense_activation": "tanh",
        "output_activation": "sigmoid",
        "optimizer": "rmsprop",
        "learning_rate": 0.004659438266599129,
        "units_lstm_3": 64,
        "units_lstm_4": 64,
        "units_lstm_5": 64,
        "units_lstm_6": 64,
        "batch_size": 32,
        "tuner/epochs": 50,
        "tuner/initial_epoch": 0,
        "tuner/bracket": 0,
        "tuner/round": 0
    },
    {
        "Model Rank": 9,
        "Trial ID": "0073",
        "train_loss": 18.999610395685135,
        "train_mse": 18.999610395685135,
        "train_rmse": 4.358854252631663,
        "train_mape": 50.20792145515007,
        "train_r2": 0.24502573629818525,
        "val_loss": 12.261289606876138,
        "val_mse": 12.261289606876138,
        "val_rmse": 3.501612429563863,
        "val_mape": 38.85357865144306,
        "val_r2": 0.5547752068150745,
        "test_loss": 2.7879333986781583,
        "test_mse": 2.7879333986781583,
        "test_rmse": 1.6697105733264548,
        "test_mape": 27.55497290974987,
        "test_r2": 0.7036085302382562,
        "num_tcnn_layers_input": 1,
        "units_lstm_0": 32,
        "dropout": 0.45,
        "num_tcnn_layers_after_input": 1,
        "units_lstm_1": 32,
        "units_lstm_2": 128,
        "dense_units": 12,
        "dense_activation": "sigmoid",
        "output_activation": "tanh",
        "optimizer": "adam",
        "learning_rate": 0.0026852909715998317,
        "units_lstm_3": 64,
        "units_lstm_4": 64,
        "units_lstm_5": 64,
        "units_lstm_6": 64,
        "batch_size": 16,
        "tuner/epochs": 50,
        "tuner/initial_epoch": 17,
        "tuner/bracket": 2,
        "tuner/round": 2,
        "tuner/trial_id": "0070"
    },
    {
        "Model Rank": 5,
        "Trial ID": "0050",
        "train_loss": 12.867216406412702,
        "train_mse": 12.867216406412702,
        "train_rmse": 3.5870902423012305,
        "train_mape": 39.33025371191781,
        "train_r2": 0.48870439814231603,
        "val_loss": 14.26820023466603,
        "val_mse": 14.26820023466603,
        "val_rmse": 3.7773271283628627,
        "val_mape": 41.64589668166154,
        "val_r2": 0.48190143922236595,
        "test_loss": 6.929095309246224,
        "test_mse": 6.929095309246224,
        "test_rmse": 2.6323174788095423,
        "test_mape": 42.58362338973109,
        "test_r2": 0.26335229392480286,
        "num_tcnn_layers_input": 3,
        "units_lstm_0": 32,
        "dropout": 0.2,
        "num_tcnn_layers_after_input": 2,
        "units_lstm_1": 128,
        "units_lstm_2": 128,
        "dense_units": 16,
        "dense_activation": "elu",
        "output_activation": "sigmoid",
        "optimizer": "adam",
        "learning_rate": 0.0018500304177758314,
        "units_lstm_3": 64,
        "units_lstm_4": 64,
        "units_lstm_5": 64,
        "units_lstm_6": 64,
        "batch_size": 24,
        "tuner/epochs": 50,
        "tuner/initial_epoch": 17,
        "tuner/bracket": 3,
        "tuner/round": 3,
        "tuner/trial_id": "0049"
    },
    {
        "Model Rank": 7,
        "Trial ID": "0085",
        "train_loss": 13.02577305022418,
        "train_mse": 13.02577305022418,
        "train_rmse": 3.609123584781239,
        "train_mape": 39.257148908752214,
        "train_r2": 0.4824039434001606,
        "val_loss": 15.611069677829294,
        "val_mse": 15.611069677829294,
        "val_rmse": 3.9510846204338996,
        "val_mape": 43.786407579097386,
        "val_r2": 0.433139947627597,
        "test_loss": 7.263518760095938,
        "test_mse": 7.263518760095938,
        "test_rmse": 2.6950916051399694,
        "test_mape": 43.830268828554075,
        "test_r2": 0.22779898473630622,
        "num_tcnn_layers_input": 1,
        "units_lstm_0": 96,
        "dropout": 0.30000000000000004,
        "num_tcnn_layers_after_input": 1,
        "units_lstm_1": 64,
        "units_lstm_2": 96,
        "dense_units": 16,
        "dense_activation": "elu",
        "output_activation": "elu",
        "optimizer": "rmsprop",
        "learning_rate": 0.0008788815784436897,
        "units_lstm_3": 64,
        "units_lstm_4": 64,
        "units_lstm_5": 64,
        "units_lstm_6": 64,
        "batch_size": 24,
        "tuner/epochs": 50,
        "tuner/initial_epoch": 0,
        "tuner/bracket": 0,
        "tuner/round": 0
    },
    {
        "Model Rank": 3,
        "Trial ID": "0051",
        "train_loss": 16.140860754449637,
        "train_mse": 16.140860754449637,
        "train_rmse": 4.017569010539786,
        "train_mape": 45.89362638836377,
        "train_r2": 0.35862187645849875,
        "val_loss": 17.336825940522434,
        "val_mse": 17.336825940522434,
        "val_rmse": 4.163751426360901,
        "val_mape": 48.436310183451766,
        "val_r2": 0.3704752932739266,
        "test_loss": 8.937853060566942,
        "test_mse": 8.937853060566942,
        "test_rmse": 2.9896242340078363,
        "test_mape": 50.105380950722875,
        "test_r2": 0.04979673962371034,
        "num_tcnn_layers_input": 2,
        "units_lstm_0": 32,
        "dropout": 0.2,
        "num_tcnn_layers_after_input": 1,
        "units_lstm_1": 32,
        "units_lstm_2": 64,
        "dense_units": 60,
        "dense_activation": "sigmoid",
        "output_activation": "elu",
        "optimizer": "adam",
        "learning_rate": 0.004659438266599129,
        "units_lstm_3": 64,
        "units_lstm_4": 64,
        "units_lstm_5": 64,
        "units_lstm_6": 64,
        "batch_size": 16,
        "tuner/epochs": 50,
        "tuner/initial_epoch": 17,
        "tuner/bracket": 3,
        "tuner/round": 3,
        "tuner/trial_id": "0046"
    },
    {
        "Model Rank": 1,
        "Trial ID": "0072",
        "train_loss": 59.31083344736089,
        "train_mse": 59.31083344736089,
        "train_rmse": 7.701352702438767,
        "train_mape": 100.0,
        "train_r2": -1.3567932120140473,
        "val_loss": 62.52169385621088,
        "val_mse": 62.52169385621088,
        "val_rmse": 7.90706607131943,
        "val_mape": 100.0,
        "val_r2": -1.2702512630557354,
        "test_loss": 31.16711909119473,
        "test_mse": 31.16711909119473,
        "test_rmse": 5.582751928143927,
        "test_mape": 100.0,
        "test_r2": -2.313446526397784,
        "num_tcnn_layers_input": 3,
        "units_lstm_0": 96,
        "dropout": 0.15000000000000002,
        "num_tcnn_layers_after_input": 3,
        "units_lstm_1": 128,
        "units_lstm_2": 96,
        "dense_units": 32,
        "dense_activation": "sigmoid",
        "output_activation": "relu",
        "optimizer": "adam",
        "learning_rate": 0.004659438266599129,
        "units_lstm_3": 64,
        "units_lstm_4": 64,
        "units_lstm_5": 64,
        "units_lstm_6": 64,
        "batch_size": 32,
        "tuner/epochs": 50,
        "tuner/initial_epoch": 17,
        "tuner/bracket": 2,
        "tuner/round": 2,
        "tuner/trial_id": "0071"
    }
]